iplotLogging/__init__.py
iplotLogging/_version.py
iplotLogging/setupLogger.py
iplotlogging-1.2.0.post1.dist-info/METADATA
iplotlogging-1.2.0.post1.dist-info/WHEEL
iplotlogging-1.2.0.post1.dist-info/top_level.txt
iplotlogging-1.2.0.post1.dist-info/RECORD
