Metadata-Version: 2.4
Name: iplotLogging
Version: 1.2.0.post1
Summary: General logging support for IDV components
Author-email: Lana Abadie <lana.abadie@iter.org>
Maintainer-email: Jhon Steeven Cabanilla Alvarado <jscabanilla@minsait.com>, Pablo Martin Villares <pmartin@minsait.com>, Mario Gómez Ballesteros <mgomezb@minsait.com>
License: MIT
Project-URL: Homepage, https://github.com/iplot-viz/iplotlogging
Project-URL: Repository, https://github.com/iplot-viz/iplotlogging.git
Project-URL: Issues, https://github.com/iplot-viz/iplotlogging/issues
Keywords: ITER logging,logs
Classifier: Programming Language :: Python :: 3
Classifier: License :: OSI Approved :: MIT License
Classifier: Operating System :: OS Independent
Requires-Python: >=3.9
Provides-Extra: test
Requires-Dist: pytest>=6.0; extra == "test"
